dataframe_api_compat/__init__.py
dataframe_api_compat/py.typed
dataframe_api_compat/utils.py
dataframe_api_compat/pandas_standard/__init__.py
dataframe_api_compat/pandas_standard/column_object.py
dataframe_api_compat/pandas_standard/dataframe_object.py
dataframe_api_compat/pandas_standard/group_by_object.py
dataframe_api_compat/pandas_standard/scalar_object.py
dataframe_api_compat/polars_standard/__init__.py
dataframe_api_compat/polars_standard/column_object.py
dataframe_api_compat/polars_standard/dataframe_object.py
dataframe_api_compat/polars_standard/group_by_object.py
dataframe_api_compat/polars_standard/scalar_object.py
dataframe_api_compat-0.2.6.dist-info/METADATA
dataframe_api_compat-0.2.6.dist-info/WHEEL
dataframe_api_compat-0.2.6.dist-info/licenses/LICENSE
dataframe_api_compat-0.2.6.dist-info/RECORD
