Metadata-Version: 2.1
Name: dataframe_api_compat
Version: 0.2.6
Summary: Implementation of the DataFrame Standard for pandas and Polars
Project-URL: Homepage, https://github.com/data-apis/dataframe-api-compat
Project-URL: Bug Tracker, https://github.com/data-apis/dataframe-api-compat
Author-email: Marco Gorelli <33491632+MarcoGorelli@users.noreply.github.com>
License-File: LICENSE
Classifier: License :: OSI Approved :: MIT License
Classifier: Operating System :: OS Independent
Classifier: Programming Language :: Python :: 3
Requires-Python: >=3.8
Requires-Dist: packaging; python_version < '3.9'
